{
    "info": {
        "id": "SB 8.8.28",
        "prevId": "SB 8.8.27",
        "nextId": "SB 8.8.29"
    },
    "verses": [
        {
            "roman": "śriyāvalokitā devāḥ\nsaprajāpatayaḥ prajāḥ\nśīlādi-guṇa-sampannā\nlebhire nirvṛtiṁ parām\n"
        }
    ],
    "synonyms": "\nśriyā—by the goddess of fortune, Lakṣmī; avalokitāḥ—being seen favorably with mercy; devāḥ—all the demigods; sa-prajāpatayaḥ—with all the prajāpatis; prajāḥ—and their generations; śīla-ādi-guṇa-sampannāḥ—all blessed with good behavior and good characteristics; lebhire—achieved; nirvṛtim—satisfaction; parām—the ultimate.\n\n",
    "translation": "\nAll the demigods, along with the prajāpatis and their descendants, being blessed by Lakṣmījī's glance upon them, were immediately enriched with good behavior and transcendental qualities. Thus they were very much satisfied.\n\n",
    "purport": null
}
