{
    "page_info": {
        "current_id": "SB 10.34.3",
        "previous_id": "SB 10.34.2",
        "next_id": "SB 10.34.4"
    },
    "verse": [
        {
            "roman": "gāvo hiraṇyaṁ vāsāṁsi\nmadhu madhv-annam ādṛtāḥ\nbrāhmaṇebhyo daduḥ sarve\ndevo naḥ prīyatām iti\n"
        }
    ],
    "synonyms": "\ngāvaḥ—cows; hiraṇyam—gold; vāsāṁsi—clothing; madhu—sweet-tasting; madhu—mixed with honey; annam—grains; ādṛtāḥ—respectfully; brāhmaṇebhyaḥ—to the brāhmaṇas; daduḥ—they gave; sarve—all of them; devaḥ—the lord; naḥ—with us; prīyatām—may be pleased; iti—thus praying.\n\n",
    "translation": "\nThe cowherd men gave the brāhmaṇas gifts of cows, gold, clothing and cooked grains mixed with honey. Then the cowherds prayed, \"May the lord be pleased with us.\"\n\n",
    "purport": null
}
