{
    "info": {
        "id": "SB 10.26.11",
        "prevId": "SB 10.26.10",
        "nextId": "SB 10.26.12"
    },
    "verses": [
        {
            "roman": "pralambaṁ ghātayitvograṁ\nbalena bala-śālinā\namocayad vraja-paśūn\ngopāṁś cāraṇya-vahnitaḥ\n"
        }
    ],
    "synonyms": "\npralambam—the demon named Pralamba; ghāyayitvā—arranging to be killed; ugram—terrible; balena—by Lord Balarāma; bala-śālinā—who is very powerful; amocayat—He liberated; vraja-paśūn—the animals of Vraja; gopān—the cowherd boys; ca—and; āraṇya—of the forest; vahnitaḥ—from the fire.\n\n",
    "translation": "\nAfter arranging for the mighty Lord Balarāma to kill the terrible demon Pralamba, Kṛṣṇa saved Vraja's cowherd boys and their animals from a forest fire.\n\n",
    "purport": null
}
