{
    "page_info": {
        "current_id": "SB 12.12.62",
        "previous_id": "SB 12.12.61",
        "next_id": "SB 12.12.63"
    },
    "verse": [
        {
            "roman": "devatā munayaḥ siddhāḥ\npitaro manavo nṛpāḥ\nyacchanti kāmān gṛṇataḥ\nśṛṇvato yasya kīrtanāt\n"
        }
    ],
    "synonyms": "\ndevatāḥ—the demigods; munayaḥ—the sages; siddhāḥ—the perfected yogīs; pitaraḥ—the forefathers; manavaḥ—the progenitors of mankind; nṛpaḥ—the kings of the earth; yacchanti—bestow; kāmān—desires; gṛṇataḥ—to one who is chanting; śṛṇvataḥ—or who is hearing; yasya—of which; kīrtanāt—because of the glorification.\n\n",
    "translation": "\nUpon the person who glorifies this Purāṇa by chanting or hearing it, the demigods, sages, Siddhas, Pitās, Manus and kings of the earth bestow all desirable things.\n\n",
    "purport": null
}
