{
    "page_info": {
        "current_id": "SB 6.13.1",
        "previous_id": "SB 6.13 Summary",
        "next_id": "SB 6.13.2"
    },
    "verse": [
        {
            "roman": "śrī-śuka uvāca\nvṛtre hate trayo lokā\nvinā śakreṇa bhūrida\nsapālā hy abhavan sadyo\nvijvarā nirvṛtendriyāḥ\n"
        }
    ],
    "synonyms": "\nśrī-śukaḥ uvāca—Śrī Śukadeva Gosvāmī said; vṛtre hate—when Vṛtrāsura was killed; trayaḥ lokāḥ—the three planetary systems (upper, middle and lower); vinā—except; śakreṇa—Indra, who is also called Śakra; bhūri-da—O Mahārāja Parīkṣit, giver of great charity; sa-pālāḥ—with the rulers of the various planets; hi—indeed; abhavan—became; sadyaḥ—immediately; vijvarāḥ—without fear of death; nirvṛta—very much pleased; indriyāḥ—whose senses.\n\n",
    "translation": "\nŚrī Śukadeva Gosvāmī said: O King Parīkṣit, who are so charitably disposed, when Vṛtrāsura was killed, all the presiding deities and everyone else in the three planetary systems was immediately pleased and free from trouble—everyone, that is, except Indra.\n\n",
    "purport": null
}
