{
    "page_info": {
        "current_id": "SB 4.9.61",
        "previous_id": "SB 4.9.60",
        "next_id": "SB 4.9.62"
    },
    "verse": [
        {
            "roman": "payaḥ-phena-nibhāḥ śayyā\ndāntā rukma-paricchadāḥ\nāsanāni mahārhāṇi\nyatra raukmā upaskarāḥ\n"
        }
    ],
    "synonyms": "\npayaḥ—milk; phena—foam; nibhāḥ—like; śayyāḥ—bedding; dāntāḥ—made of ivory; rukma—golden; paricchadāḥ—with embellishments; āsanāni—sitting places; mahā-arhāṇi—very valuable; yatra—where; raukmāḥ—golden; upaskarāḥ—furniture.\n\n",
    "translation": "\nThe bedding in the palace was as white as the foam of milk and was very soft. The bedsteads were made of ivory with embellishments of gold, and the chairs, benches and other sitting places and furniture were made of gold.\n\n",
    "purport": null
}
