{
    "page_info": {
        "current_id": "SB 11.24.16",
        "previous_id": "SB 11.24.15",
        "next_id": "SB 11.24.17"
    },
    "verse": [
        {
            "roman": "aṇur bṛhat kṛśaḥ sthūlo\nyo yo bhāvaḥ prasidhyati\nsarvo 'py ubhaya-saṁyuktaḥ\nprakṛtyā puruṣeṇa ca\n"
        }
    ],
    "synonyms": "\naṇuḥ—small; bṛhat—great; kṛśaḥ—thin; sthūlaḥ—stout; yaḥ yaḥ—whatever; bhāvaḥ—manifestation; prasidhyati—is established; sarvaḥ—all; api—indeed; ubhaya—by both; saṁyuktaḥ—conjoined; prakṛtyā—by nature; puruṣeṇa—by the enjoying spirit soul; ca—and.\n\n",
    "translation": "\nWhatever features visibly exist within this world—small or great, thin or stout—certainly contain both the material nature and its enjoyer, the spirit soul.\n\n",
    "purport": null
}
