{
    "info": {
        "id": "SB 11.22.60",
        "prevId": "SB 11.22.58-59",
        "nextId": "SB 11.22.61"
    },
    "verses": [
        {
            "roman": "śrī-uddhava uvāca\nyathaivam anubudhyeyaṁ\nvada no vadatāṁ vara\n"
        }
    ],
    "synonyms": "\nśrī-uddhavaḥ uvāca—Śrī Uddhava said; yathā—how; evam—thus; anubudhyeyam—I may properly understand; vada—please speak; naḥ—to us; vadatām—of all speakers; vara—O You who are the best.\n\n",
    "translation": "\nŚrī Uddhava said: O best of all speakers, please explain to me how I may properly understand this.\n\n",
    "purport": null
}
