{
    "info": {
        "id": "SB 10.73.22",
        "prevId": "SB 10.73.21",
        "nextId": "SB 10.73.23"
    },
    "verses": [
        {
            "roman": "santanvantaḥ prajā-tantūn\nsukhaṁ duḥkhaṁ bhavābhavau\nprāptaṁ prāptaṁ ca sevanto\nmac-cittā vicariṣyatha\n"
        }
    ],
    "synonyms": "\nsantanvantaḥ—generating; prajā—of progeny; tantūn—lines; sukham—happiness; duḥkham—distress; bhava—birth; abhavau—and death; prāptam prāptam—as they are encountered; ca—and; sevantaḥ—accepting; mat-cittāḥ—with minds fixed on Me; vicariṣyatha—you should go about.\n\n",
    "translation": "\nAs you live your lives, begetting generations of progeny and encountering happiness and distress, birth and death, always keep your minds fixed on Me.\n\n",
    "purport": null
}
