{
    "page_info": {
        "current_id": "SB 10.46.7",
        "previous_id": "SB 10.46.6",
        "next_id": "SB 10.46.8"
    },
    "verse": [
        {
            "roman": "śrī-śuka uvāca\nity ukta uddhavo rājan\nsandeśaṁ bhartur ādṛtaḥ\nādāya ratham āruhya\nprayayau nanda-gokulam\n"
        }
    ],
    "synonyms": "\nśrī-śukaḥ uvāca—Śukadeva Gosvāmī said; iti—thus; uktaḥ—spoken to; uddhavaḥ—Uddhava; rājan—O King (Parīkṣit); sandeśam—the message; bhartuḥ—of his master; ādṛtaḥ—respectfully; ādāya—taking; ratham—his chariot; āruhya—mounting; prayayau—went off; nanda-gokulam—to the cowherd village of Nanda Mahārāja.\n\n",
    "translation": "\nŚukadeva Gosvāmī said: Thus addressed, O King, Uddhava respectfully accepted his master's message, mounted his chariot and set off for Nanda-gokula.\n\n",
    "purport": null
}
