{
    "page_info": {
        "current_id": "SB 10.19.4",
        "previous_id": "SB 10.19.3",
        "next_id": "SB 10.19.5"
    },
    "verse": [
        {
            "roman": "tṛṇais tat-khura-dac-chinnair\ngoṣ-padair aṅkitair gavām\nmārgam anvagaman sarve\nnaṣṭājīvyā vicetasaḥ\n"
        }
    ],
    "synonyms": "\ntṛṇaiḥ—by the blades of grass; tat—of those cows; khura—by the hooves; dat—and the teeth; chinnaiḥ—which were broken; goḥ-padaiḥ—with the hoofprints; aṅkitaiḥ—(by places in the ground) which were marked; gavām—of the cows; mārgam—the path; anvagaman—they followed; sarve—all of them; naṣṭa-ājīvyāḥ—having lost their livelihood; vicetasaḥ—in anxiety.\n\n",
    "translation": "\nThen the boys began tracing out the cows' path by noting their hoofprints and the blades of grass the cows had broken with their hooves and teeth. All the cowherd boys were in great anxiety because they had lost their source of livelihood.\n\n",
    "purport": null
}
