{
    "info": {
        "id": "SB 4.29.12",
        "prevId": "SB 4.29.11",
        "nextId": "SB 4.29.13"
    },
    "verses": [
        {
            "roman": "āpaṇo vyavahāro 'tra\ncitram andho bahūdanam\npitṛhūr dakṣiṇaḥ karṇa\nuttaro devahūḥ smṛtaḥ\n"
        }
    ],
    "synonyms": "\nāpaṇaḥ—named Āpaṇa; vyavahāraḥ—business of the tongue; atra—here; citram—of all varieties; andhaḥ—eatables; bahūdanam—named Bahūdana; pitṛ-hūḥ—named Pitṛhū; dakṣiṇaḥ—right; karṇaḥ—ear; uttaraḥ—left; deva-hūḥ—Devahū; smṛtaḥ—is called.\n\n",
    "translation": "\nThe city called Āpaṇa represents engagement of the tongue in speech, and Bahūdana is the variety of foodstuffs. The right ear is called the gate of Pitṛhū, and the left ear is called the gate of Devahū.\n\n",
    "purport": null
}
