{
    "page_info": {
        "current_id": "SB 10.73.33",
        "previous_id": "SB 10.73.32",
        "next_id": "SB 10.73.34"
    },
    "verse": [
        {
            "roman": "tac chrutvā prīta-manasa\nindraprastha-nivāsinaḥ\nmenire māgadhaṁ śāntaṁ\nrājā cāpta-manorathaḥ\n"
        }
    ],
    "synonyms": "\ntat—that; śrutvā—hearing; prīta—pleased; manasaḥ—in their hearts; indraprastha-nivāsinaḥ—the residents of Indraprastha; menire—understood; māgadham—Jarāsandha; śāntam—put to rest; rājā—the King (Yudhiṣṭhira); ca—and; āpta—achieved; manaḥ-rathaḥ—whose desires.\n\n",
    "translation": "\nThe residents of Indraprastha were very pleased to hear that sound, for they understood that now the King of Magadha had been put to rest. King Yudhiṣṭhira felt that his desires were now fulfilled.\n\n",
    "purport": null
}
